conventional/__init__.py
conventional/__main__.py
conventional/cli.py
conventional/commands/__init__.py
conventional/commands/exceptions.py
conventional/commands/list_commits.py
conventional/commands/parse_commit.py
conventional/commands/parse_commit_test.py
conventional/commands/template.py
conventional/config_default.yaml
conventional/git.py
conventional/git_test.py
conventional/parser/__init__.py
conventional/parser/base.py
conventional/parser/base_test.py
conventional/parser/conventional_commits.py
conventional/parser/conventional_commits_test.py
conventional/templates/changelog.md
conventional/templates/conventional-commit
conventional/templates/slack.md
conventional/util/__init__.py
conventional/util/config.py
conventional/util/confuse.py
conventional/util/io.py
conventional/util/typer.py
conventional-0.6.0.dist-info/entry_points.txt
conventional-0.6.0.dist-info/LICENSE
conventional-0.6.0.dist-info/WHEEL
conventional-0.6.0.dist-info/METADATA
conventional-0.6.0.dist-info/RECORD
