Metadata-Version: 2.1
Name: conventional
Version: 0.6.0
Summary: No frills command-line tool for processing structured commits.
Home-page: https://github.com/multimac/conventional
License: MIT
Author: David Symons
Author-email: david@symons.io
Requires-Python: >=3.8,<4.0
Classifier: Development Status :: 4 - Beta
Classifier: Environment :: Console
Classifier: Intended Audience :: Developers
Classifier: License :: OSI Approved :: MIT License
Classifier: Programming Language :: Python :: 3
Classifier: Programming Language :: Python :: 3.10
Classifier: Programming Language :: Python :: 3.8
Classifier: Programming Language :: Python :: 3.9
Classifier: Topic :: Software Development :: Build Tools
Classifier: Topic :: Software Development :: Version Control :: Git
Requires-Dist: aiocache (>=0.11.1,<0.12.0)
Requires-Dist: colorama (>=0.4.3,<0.5.0)
Requires-Dist: confuse (>=1.1.0,<2.0.0)
Requires-Dist: jinja2 (>=3.0.3,<4.0.0)
Requires-Dist: python-dateutil (>=2.8.1,<3.0.0)
Requires-Dist: typer (>=0.3,<0.4)
